{"name":"As a user with an active matex I want to check if I am exempt from paying for prescriptions","id":"matex-scenarios;as-a-user-with-an-active-matex-i-want-to-check-if-i-am-exempt-from-paying-for-prescriptions","scenarioId":"matex:As a user with an active matex I want to check if I am exempt from paying for prescriptions","methodName":"As a user with an active matex I want to check if I am exempt from paying for prescriptions","testSteps":[{"number":1,"description":"Given I am checking to see if I am exempt from paying for prescriptions","duration":3144,"startTime":"2025-09-06T15:35:22.704586+01:00[Europe/London]","result":"SUCCESS","precondition":false,"level":0},{"number":2,"description":"When my date of birth is \"21\" \"09\" \"1995\"","duration":843,"startTime":"2025-09-06T15:35:25.849584+01:00[Europe/London]","result":"SUCCESS","precondition":false,"level":0},{"number":3,"description":"And my firstname is \"testE\" and my lastname is \"Smith\"","duration":548,"startTime":"2025-09-06T15:35:26.693089+01:00[Europe/London]","result":"SUCCESS","precondition":false,"level":0},{"number":4,"description":"And my postcode is \"L15 3JY\"","duration":1066,"startTime":"2025-09-06T15:35:27.241618+01:00[Europe/London]","result":"SUCCESS","precondition":false,"level":0},{"number":5,"description":"Then I should see that I am exempt from prescriptions and dental check-ups","duration":80,"startTime":"2025-09-06T15:35:28.308609+01:00[Europe/London]","result":"SUCCESS","precondition":false,"level":0},{"number":6,"description":"Given I am checking to see if I am exempt from paying for prescriptions","duration":249,"startTime":"2025-09-06T15:35:28.394540+01:00[Europe/London]","result":"SUCCESS","precondition":false,"level":0},{"number":7,"description":"When my date of birth is \"21\" \"09\" \"1995\"","duration":702,"startTime":"2025-09-06T15:35:28.643878+01:00[Europe/London]","result":"SUCCESS","precondition":false,"level":0},{"number":8,"description":"And my firstname is \"testB\" and my lastname is \"Swallow\"","duration":546,"startTime":"2025-09-06T15:35:29.347045+01:00[Europe/London]","result":"SUCCESS","precondition":false,"level":0},{"number":9,"description":"And my postcode is \"L15 3JY\"","duration":790,"startTime":"2025-09-06T15:35:29.893325+01:00[Europe/London]","result":"SUCCESS","precondition":false,"level":0},{"number":10,"description":"Then I should see that I am exempt from prescriptions and dental check-ups","duration":73,"startTime":"2025-09-06T15:35:30.684440+01:00[Europe/London]","result":"SUCCESS","precondition":false,"level":0}],"userStory":{"id":"matex","storyName":"Matex Scenarios","displayName":"Matex Scenarios","path":"matex","pathElements":[{"name":"matex","description":""}],"type":"feature"},"title":"As a user with an active matex I want to check if I am exempt from paying for prescriptions","description":"","tags":[{"name":"Chrome","type":"context","displayName":"Chrome"},{"name":"Mac","type":"context","displayName":"Mac"},{"name":"Chrome, Mac","type":"context","displayName":"Chrome, Mac"}],"startTime":"2025-09-06T15:35:22.704259+01:00[Europe/London]","endTime":"2025-09-06T15:35:30.757708+01:00[Europe/London]","duration":3144,"projectKey":"","sessionId":"dd72c4578d3df8d44d22c1b1238e339a","driver":"chrome","isManualTestingUpToDate":false,"context":"chrome,mac","manual":false,"testSource":"Cucumber","order":0,"result":"SUCCESS"}